app.py
heroku_flask.py
wsgi.py
heroku_flask-0.0.1.data/scripts/heroku_flask.bat
heroku_flask-0.0.1.data/scripts/heroku_flask.sh
heroku_flask-0.0.1.dist-info/METADATA
heroku_flask-0.0.1.dist-info/WHEEL
heroku_flask-0.0.1.dist-info/top_level.txt
heroku_flask-0.0.1.dist-info/RECORD
