Metadata-Version: 2.1
Name: heroku-flask
Version: 0.0.1
Summary: Heroku setup for flask application
Home-page: https://github.com/AbhimanyuHK/heroku-flask
Author: Abhimanyu HK
Author-email: manyu1994@hotmail.com
License: UNKNOWN
Platform: UNKNOWN
